{
  "settings": {
    "components": {
      "code": true,
      "binaries": false
    },
    "targetId": "net10.0",
    "targetDisplayName": ".NETCoreApp,Version=v10.0"
  },
  "analysisStartTime": "2026-04-10T20:28:16.247825Z",
  "analysisEndTime": "2026-04-10T20:28:24.3719526Z",
  "privacyModeHelpUrl": "https://go.microsoft.com/fwlink/?linkid=2270980",
  "stats": {
    "summary": {
      "projects": 3,
      "issues": 1,
      "incidents": 3,
      "effort": 3
    },
    "charts": {
      "severity": {
        "Mandatory": 3,
        "Optional": 0,
        "Potential": 0,
        "Information": 0
      },
      "category": {
        "Project": 3
      }
    }
  },
  "projects": [
    {
      "path": "samples\\BasicSample\\BasicSample.csproj",
      "startingProject": true,
      "issues": 1,
      "storyPoints": 1,
      "properties": {
        "appName": "BasicSample",
        "projectKind": "DotNetCoreApp",
        "frameworks": [
          "net6.0"
        ],
        "languages": [
          "C#"
        ],
        "tools": [
          "MSBuild"
        ],
        "isSdkStyle": true,
        "numberOfFiles": 1,
        "numberOfCodeFiles": 1,
        "linesTotal": 149,
        "linesOfCode": 149,
        "totalApiScanned": 114,
        "minLinesOfCodeToChange": 0,
        "maxLinesOfCodeToChange": 0
      },
      "ruleInstances": [
        {
          "incidentId": "c5df86fe-e950-4a4f-8f13-f7ef58905262",
          "ruleId": "Project.0002",
          "projectPath": "samples\\BasicSample\\BasicSample.csproj",
          "state": "Active",
          "location": {
            "snippetModel": {
              "unrestricted": "Current target framework: net6.0\nRecommended target framework: net10.0",
              "protected": "Current target framework: net6.0\nRecommended target framework: net10.0"
            },
            "kind": "File",
            "path": "samples\\BasicSample\\BasicSample.csproj",
            "snippet": "Current target framework: net6.0\nRecommended target framework: net10.0",
            "protectedSnippet": "Current target framework: net6.0\nRecommended target framework: net10.0",
            "properties": {
              "CurrentTargetFramework": "net6.0",
              "RecommendedTargetFramework": "net10.0"
            }
          }
        }
      ],
      "features": []
    },
    {
      "path": "src\\XpoSapHana\\XpoSapHana.csproj",
      "startingProject": true,
      "issues": 1,
      "storyPoints": 1,
      "properties": {
        "appName": "XpoSapHana",
        "projectKind": "ClassLibrary",
        "frameworks": [
          "net6.0"
        ],
        "languages": [
          "C#"
        ],
        "tools": [
          "MSBuild"
        ],
        "isSdkStyle": true,
        "numberOfFiles": 4,
        "numberOfCodeFiles": 4,
        "linesTotal": 442,
        "linesOfCode": 442,
        "totalApiScanned": 477,
        "minLinesOfCodeToChange": 0,
        "maxLinesOfCodeToChange": 0
      },
      "ruleInstances": [
        {
          "incidentId": "52a0435c-c86a-41de-87d9-c25991966fe3",
          "ruleId": "Project.0002",
          "projectPath": "src\\XpoSapHana\\XpoSapHana.csproj",
          "state": "Active",
          "location": {
            "snippetModel": {
              "unrestricted": "Current target framework: net6.0\nRecommended target framework: net10.0",
              "protected": "Current target framework: net6.0\nRecommended target framework: net10.0"
            },
            "kind": "File",
            "path": "src\\XpoSapHana\\XpoSapHana.csproj",
            "snippet": "Current target framework: net6.0\nRecommended target framework: net10.0",
            "protectedSnippet": "Current target framework: net6.0\nRecommended target framework: net10.0",
            "properties": {
              "CurrentTargetFramework": "net6.0",
              "RecommendedTargetFramework": "net10.0"
            }
          }
        }
      ],
      "features": []
    },
    {
      "path": "tests\\XpoSapHana.Tests\\XpoSapHana.Tests.csproj",
      "startingProject": true,
      "issues": 1,
      "storyPoints": 1,
      "properties": {
        "appName": "XpoSapHana.Tests",
        "projectKind": "DotNetCoreApp",
        "frameworks": [
          "net6.0"
        ],
        "languages": [
          "C#"
        ],
        "tools": [
          "MSBuild"
        ],
        "isSdkStyle": true,
        "numberOfFiles": 3,
        "numberOfCodeFiles": 1,
        "linesTotal": 1982,
        "linesOfCode": 207,
        "totalApiScanned": 213,
        "minLinesOfCodeToChange": 0,
        "maxLinesOfCodeToChange": 0
      },
      "ruleInstances": [
        {
          "incidentId": "01ab04d8-abee-45c9-8840-51372c1d99b6",
          "ruleId": "Project.0002",
          "projectPath": "tests\\XpoSapHana.Tests\\XpoSapHana.Tests.csproj",
          "state": "Active",
          "location": {
            "snippetModel": {
              "unrestricted": "Current target framework: net6.0\nRecommended target framework: net10.0",
              "protected": "Current target framework: net6.0\nRecommended target framework: net10.0"
            },
            "kind": "File",
            "path": "tests\\XpoSapHana.Tests\\XpoSapHana.Tests.csproj",
            "snippet": "Current target framework: net6.0\nRecommended target framework: net10.0",
            "protectedSnippet": "Current target framework: net6.0\nRecommended target framework: net10.0",
            "properties": {
              "CurrentTargetFramework": "net6.0",
              "RecommendedTargetFramework": "net10.0"
            }
          }
        }
      ],
      "features": []
    }
  ],
  "rules": {
    "Project.0002": {
      "id": "Project.0002",
      "isFeature": false,
      "description": "Project\u0027s target framework(s) needs to be changed to the new target framework that you selected for this upgrade.\n\nDuring upgrade target framework will be adjusted to corresponding platform when applicable. In some cases project would result in multiple target frameworks after the upgrade if it was using features that now have their own platforms in modern .NET frameworks (windows, iOS, Android etc).",
      "label": "Project\u0027s target framework(s) needs to be changed",
      "severity": "Mandatory",
      "effort": 1,
      "links": [
        {
          "title": "Overview of porting from .NET Framework to .NET",
          "url": "https://go.microsoft.com/fwlink/?linkid=2265227",
          "isCustom": false
        },
        {
          "title": ".NET project SDKs",
          "url": "https://go.microsoft.com/fwlink/?linkid=2265226",
          "isCustom": false
        }
      ]
    }
  }
}